selenium_assist/__init__.py
selenium_assist/helpers.py
selenium_assist/managers.py
selenium_assist/wrappers.py
selenium_assist-0.3.5.dist-info/METADATA
selenium_assist-0.3.5.dist-info/WHEEL
selenium_assist-0.3.5.dist-info/licenses/LICENSE
selenium_assist-0.3.5.dist-info/RECORD
