Metadata-Version: 2.3
Name: selenium_assist
Version: 0.3.5
Summary: Helper functions for Selenium
Project-URL: Homepage, https://github.com/ivanmicetic/selenium-assist
Project-URL: Bug Tracker, https://github.com/ivanmicetic/selenium-assist/issues
Author-email: Ivan Mičetić <ivan.micetic@gmail.com>
License-File: LICENSE
Classifier: Development Status :: 3 - Alpha
Classifier: Intended Audience :: Developers
Classifier: License :: OSI Approved :: MIT License
Classifier: Operating System :: OS Independent
Classifier: Programming Language :: Python :: 3
Classifier: Topic :: Software Development :: Libraries :: Python Modules
Requires-Python: >=3.7
Requires-Dist: selenium>3
Requires-Dist: webdriver-manager
